README.md
setup.py
GeoUnitMergerDI/Merger.py
GeoUnitMergerDI/__init__.py
GeoUnitMergerDI.egg-info/PKG-INFO
GeoUnitMergerDI.egg-info/SOURCES.txt
GeoUnitMergerDI.egg-info/dependency_links.txt
GeoUnitMergerDI.egg-info/requires.txt
GeoUnitMergerDI.egg-info/top_level.txt